{
  "project_info": {
    "project_number": "521977987330",
    "project_id": "appit-d5b5e",
    "storage_bucket": "appit-d5b5e.firebasestorage.app"
  },
  "client": [
    {
      "client_info": {
        "mobilesdk_app_id": "1:521977987330:android:ecdc78ca379144b973c21b",
        "android_client_info": {
          "package_name": "com.example.appit"
        }
      },
      "oauth_client": [
        {
          "client_id": "521977987330-fb0mfuela9uuaktqvkorjg6hlqjea34h.apps.googleusercontent.com",
          "client_type": 1,
          "android_info": {
            "package_name": "com.example.appit",
            "certificate_hash": "2600016869c81c42b4dd6ea369acebe7b9f6df16"
          }
        },
        {
          "client_id": "521977987330-42odvjniuqq39e8r9h19imjh8loehuls.apps.googleusercontent.com",
          "client_type": 3
        }
      ],
      "api_key": [
        {
          "current_key": "AIzaSyD6lNWT0hSTvCdTdkbXX7lJ-prwlNKUUWA"
        }
      ],
      "services": {
        "appinvite_service": {
          "other_platform_oauth_client": [
            {
              "client_id": "521977987330-42odvjniuqq39e8r9h19imjh8loehuls.apps.googleusercontent.com",
              "client_type": 3
            }
          ]
        }
      }
    }
  ],
  "configuration_version": "1"
}